docs/run_live_docs_server.py
docs/source/conf.py
polars_extensions/__init__.py
polars_extensions/biology.py
polars_extensions/geo.py
polars_extensions/io.py
polars_extensions/name.py
polars_extensions/numeric.py
polars_extensions/string.py
polars_extensions/technical_analysis.py
polars_extensions/units.py
polars_extensions/url.py
polars_extensions/mssql/__init__.py
polars_extensions/mssql/types.py
polars_extensions/mssql/writer.py
polars_extensions-1.4.1.dist-info/licenses/LICENSE
tests/test_biology.py
tests/test_geo.py
tests/test_io.py
tests/test_mssql_types.py
tests/test_mssql_writer.py
tests/test_name.py
tests/test_numeric.py
tests/test_string.py
tests/test_technical_analysis.py
tests/test_units.py
tests/test_url.py
polars_extensions-1.4.1.dist-info/METADATA
polars_extensions-1.4.1.dist-info/WHEEL
polars_extensions-1.4.1.dist-info/top_level.txt
polars_extensions-1.4.1.dist-info/RECORD
