Metadata-Version: 2.4
Name: polars-extensions
Version: 1.4.1
Summary: The Library of Polars Extensions
Author-email: Jayden Rasband <jayden.rasband@gmail.com>
License: MIT
Project-URL: Source, https://github.com/jrasband-dev/polars-extensions
Project-URL: Documentation, https://jrasband-dev.github.io/polars-extensions/
License-File: LICENSE
Requires-Dist: polars
Requires-Dist: defusedxml
Requires-Dist: pyodbc
Requires-Dist: tqdm
Dynamic: license-file
